uldaq/__init__.py
uldaq/ai_config.py
uldaq/ai_device.py
uldaq/ai_info.py
uldaq/ao_config.py
uldaq/ao_device.py
uldaq/ao_info.py
uldaq/buffer_management.py
uldaq/ctr_config.py
uldaq/ctr_device.py
uldaq/ctr_info.py
uldaq/daq_device.py
uldaq/daq_device_config.py
uldaq/daq_device_discovery.py
uldaq/daq_device_info.py
uldaq/daqi_device.py
uldaq/daqi_info.py
uldaq/daqo_device.py
uldaq/daqo_info.py
uldaq/dev_mem_info.py
uldaq/dio_config.py
uldaq/dio_device.py
uldaq/dio_info.py
uldaq/tmr_device.py
uldaq/tmr_info.py
uldaq/ul_c_interface.py
uldaq/ul_enums.py
uldaq/ul_exception.py
uldaq/ul_structs.py
uldaq/utils.py
uldaq-1.2.2.dist-info/DESCRIPTION.rst
uldaq-1.2.2.dist-info/METADATA
uldaq-1.2.2.dist-info/RECORD
uldaq-1.2.2.dist-info/WHEEL
uldaq-1.2.2.dist-info/metadata.json
uldaq-1.2.2.dist-info/top_level.txt
