Metadata-Version: 1.1
Name: uldaq
Version: 1.2.2
Summary: Universal Library Python API for Measurement Computing DAQ devices
Home-page: http://www.mccdaq.com
Author: Measurement Computing
Author-email: info@mccdaq.com
License: MIT
Keywords: uldaq,mcc,ul,daq,data,acquisition
Platform: UNKNOWN
Classifier: Development Status :: 5 - Production/Stable
Classifier: Intended Audience :: Developers
Classifier: Intended Audience :: Manufacturing
Classifier: Intended Audience :: Science/Research
Classifier: License :: OSI Approved :: MIT License
Classifier: Operating System :: POSIX
Classifier: Programming Language :: Python :: 2
Classifier: Programming Language :: Python :: 2.7
Classifier: Programming Language :: Python :: 3
Classifier: Programming Language :: Python :: 3.4
Classifier: Programming Language :: Python :: 3.5
Classifier: Programming Language :: Python :: 3.6
Classifier: Topic :: System :: Hardware :: Hardware Drivers
